geo_data_br/__init__.py
geo_data_br/points.py
geo_data_br/test/__init__.py
geo_data_br/test/test_feature1.py
geo_data_br/test/test_geo_data_br.py
geo_data_br-0.3.5.dist-info/AUTHORS
geo_data_br-0.3.5.dist-info/LICENSE
geo_data_br-0.3.5.dist-info/METADATA
geo_data_br-0.3.5.dist-info/WHEEL
geo_data_br-0.3.5.dist-info/pbr.json
geo_data_br-0.3.5.dist-info/top_level.txt
geo_data_br-0.3.5.dist-info/RECORD
