Metadata-Version: 2.1
Name: geo-data-br
Version: 0.3.5
Summary: UNKNOWN
Home-page: https://github.com/polvoazul/geo-data-br
Author: Fred Israel
License: UNKNOWN
Download-URL: https://github.com/polvoazul/geo-data-br
Keywords: datascience,brazil
Platform: UNKNOWN
Classifier: Intended Audience :: Developers
Classifier: Operating System :: OS Independent
Requires-Python: >=3.7
Requires-Dist: joblib
Requires-Dist: shapely
Requires-Dist: importlib-metadata
Requires-Dist: appdirs
